valanga/__init__.py
valanga/evaluations.py
valanga/evaluator_types.py
valanga/game.py
valanga/over_event.py
valanga/policy.py
valanga/progress_messsage.py
valanga/py.typed
valanga/representation_factory.py
valanga/represention_for_evaluation.py
valanga-0.1.13.dist-info/licenses/LICENSE
valanga-0.1.13.dist-info/METADATA
valanga-0.1.13.dist-info/WHEEL
valanga-0.1.13.dist-info/top_level.txt
valanga-0.1.13.dist-info/RECORD
