Metadata-Version: 2.4
Name: valanga
Version: 0.1.13
Summary: Shared types and utilities for evaluation
Author-email: Victor Gabillon <victorgabillon@gmail.com>
License:                     GNU GENERAL PUBLIC LICENSE
Classifier: Programming Language :: Python :: 3
Classifier: Programming Language :: Python :: 3.13
Requires-Python: >=3.13
License-File: LICENSE
Provides-Extra: test
Requires-Dist: pytest>=8.4.1; extra == "test"
Requires-Dist: coverage; extra == "test"
Requires-Dist: pytest-cov>=6.0.0; extra == "test"
Provides-Extra: lint
Requires-Dist: ruff>=0.14.10; extra == "lint"
Requires-Dist: pylint>=4.0.4; extra == "lint"
Provides-Extra: typecheck
Requires-Dist: mypy>=1.19.1; extra == "typecheck"
Requires-Dist: pyright[nodejs]>=1.1.408; extra == "typecheck"
Provides-Extra: dev
Requires-Dist: tox>=4.32.0; extra == "dev"
Requires-Dist: types-PyYAML>=6.0.12.12; extra == "dev"
Requires-Dist: ruff>=0.14.10; extra == "dev"
Requires-Dist: pylint>=4.0.4; extra == "dev"
Requires-Dist: black>=25.12.0; extra == "dev"
Requires-Dist: mypy>=1.19.1; extra == "dev"
Requires-Dist: pyright[nodejs]>=1.1.408; extra == "dev"
Requires-Dist: build; extra == "dev"
Requires-Dist: twine; extra == "dev"
Requires-Dist: sphinx; extra == "dev"
Requires-Dist: sphinx-rtd-theme; extra == "dev"
Requires-Dist: sphinx-autodoc-typehints; extra == "dev"
Requires-Dist: pre-commit; extra == "dev"
Dynamic: license-file
